monarchmoney/__init__.py
monarchmoney/monarchmoney.py
monarchmoney-0.1.15.dist-info/LICENSE
monarchmoney-0.1.15.dist-info/METADATA
monarchmoney-0.1.15.dist-info/WHEEL
monarchmoney-0.1.15.dist-info/top_level.txt
monarchmoney-0.1.15.dist-info/RECORD
