Metadata-Version: 2.2
Name: monarchmoney
Version: 0.1.15
Summary: Monarch Money API for Python
Home-page: https://github.com/hammem/monarchmoney
Author: hammem
Author-email: hammem@users.noreply.github.com
License: MIT
Keywords: monarch money,financial,money,personal finance
Platform: any
Classifier: Development Status :: 4 - Beta
Classifier: Intended Audience :: Developers
Classifier: Intended Audience :: Financial and Insurance Industry
Classifier: License :: OSI Approved :: MIT License
Classifier: Topic :: Office/Business :: Financial
License-File: LICENSE
Requires-Dist: aiohttp>=3.8.4
Requires-Dist: gql>=3.4
Requires-Dist: oathtool>=2.3.1
Dynamic: author
Dynamic: author-email
Dynamic: classifier
Dynamic: description
Dynamic: description-content-type
Dynamic: home-page
Dynamic: keywords
Dynamic: license
Dynamic: platform
Dynamic: requires-dist
Dynamic: summary
